quantmod/__init__.py
quantmod/_version.py
quantmod/main.py
quantmod/utils.py
quantmod/datasets/__init__.py
quantmod/datasets/dataloader.py
quantmod/derivatives/__init__.py
quantmod/derivatives/options.py
quantmod/indicators/__init__.py
quantmod/indicators/indicators.py
quantmod/markets/__init__.py
quantmod/markets/bb.py
quantmod/markets/yahoo.py
quantmod/models/__init__.py
quantmod/models/blackscholes.py
quantmod/models/montecarlo.py
quantmod/models/optioninputs.py
quantmod/risk/__init__.py
quantmod/risk/riskinputs.py
quantmod/risk/var.py
quantmod/risk/varbacktester.py
quantmod/timeseries/__init__.py
quantmod/timeseries/performance.py
quantmod/timeseries/timeseries.py
quantmod_python-0.0.4.dist-info/LICENSE.txt
quantmod_python-0.0.4.dist-info/METADATA
quantmod_python-0.0.4.dist-info/WHEEL
quantmod_python-0.0.4.dist-info/entry_points.txt
quantmod_python-0.0.4.dist-info/top_level.txt
quantmod_python-0.0.4.dist-info/RECORD
