Metadata-Version: 2.1
Name: quantmod-python
Version: 0.0.4
Summary: Quantmod Python Package
Home-page: https://kannansingaravelu.com/
Author: Kannan Singaravelu
Author-email: inquant@outlook.com
License: Apache License 2.0
Keywords: python,quant,quantmod,quantmod-python
Platform: any
Classifier: License :: OSI Approved :: Apache Software License
Classifier: Programming Language :: Python :: 3
Classifier: Programming Language :: Python :: 3.9
Classifier: Programming Language :: Python :: 3.10
Classifier: Operating System :: OS Independent
Classifier: Intended Audience :: Developers
Classifier: Topic :: Office/Business :: Financial
Classifier: Topic :: Office/Business :: Financial :: Investment
Classifier: Topic :: Software Development :: Libraries
Classifier: Topic :: Software Development :: Libraries :: Python Modules
Requires-Python: >=3.9
License-File: LICENSE.txt
Requires-Dist: numpy>=2.0.2
Requires-Dist: pandas>=2.2.2
Requires-Dist: pydantic>=2.8.2
Requires-Dist: quantmod
Requires-Dist: scipy>=1.13.1
Requires-Dist: tabulate>=0.9.0
Requires-Dist: urllib3==1.26.15
Requires-Dist: yfinance>=0.2.43
